option_combos/EWMA.py
option_combos/GBS.py
option_combos/GBS_greek_test.py
option_combos/GBSx.py
option_combos/__init__.py
option_combos/combos.py
option_combos/defaults.py
option_combos/instruments.py
option_combos/merton_model.py
option_combos/portfolio.py
option_combos-0.9.3.dist-info/LICENSE
option_combos-0.9.3.dist-info/METADATA
option_combos-0.9.3.dist-info/WHEEL
option_combos-0.9.3.dist-info/top_level.txt
option_combos-0.9.3.dist-info/RECORD
