Metadata-Version: 2.1
Name: option_combos
Version: 0.9.3
Summary: Black Scholes for options portfolios combos
Author: Jayanth R. Varma, Vineet Virmani
Maintainer-email: "Jayanth R. Varma" <jrvarma@gmail.com>
License: OSI Approved :: GNU General Public License (GPL)
Project-URL: Homepage, https://github.com/jrvarma/option_combos
Keywords: Black Scholes,Options,Option Greeks,Option Portfolios,Payoff Plots
Classifier: Development Status :: 3 - Alpha
Classifier: Environment :: Console
Classifier: Intended Audience :: End Users/Desktop
Classifier: Programming Language :: Python :: 3
Requires-Python: >=3.0
License-File: LICENSE
Requires-Dist: numpy
Requires-Dist: pandas
Requires-Dist: scipy
